onnx_to_gurobi/__init__.py
onnx_to_gurobi/internalOnnx.py
onnx_to_gurobi/onnxToGurobi.py
onnx_to_gurobi/parser.py
onnx_to_gurobi/utils.py
onnx_to_gurobi/operators/__init__.py
onnx_to_gurobi/operators/add.py
onnx_to_gurobi/operators/averagepool.py
onnx_to_gurobi/operators/base_operator.py
onnx_to_gurobi/operators/batch_normalization.py
onnx_to_gurobi/operators/concat.py
onnx_to_gurobi/operators/conv.py
onnx_to_gurobi/operators/dropout.py
onnx_to_gurobi/operators/flatten.py
onnx_to_gurobi/operators/gemm.py
onnx_to_gurobi/operators/identity.py
onnx_to_gurobi/operators/matmul.py
onnx_to_gurobi/operators/maxpool.py
onnx_to_gurobi/operators/operator_factory.py
onnx_to_gurobi/operators/relu.py
onnx_to_gurobi/operators/reshape.py
onnx_to_gurobi/operators/sub.py
onnx_to_gurobi/operators/unsqueeze.py
onnx_to_gurobi/parsers/__init__.py
onnx_to_gurobi/parsers/add_parser.py
onnx_to_gurobi/parsers/averagepool_parser.py
onnx_to_gurobi/parsers/base_parser.py
onnx_to_gurobi/parsers/batch_normalization_parser.py
onnx_to_gurobi/parsers/concat_parser.py
onnx_to_gurobi/parsers/constant_parser.py
onnx_to_gurobi/parsers/conv_parser.py
onnx_to_gurobi/parsers/dropout_parser.py
onnx_to_gurobi/parsers/flatten_parser.py
onnx_to_gurobi/parsers/gemm_parser.py
onnx_to_gurobi/parsers/identity_parser.py
onnx_to_gurobi/parsers/matmul_parser.py
onnx_to_gurobi/parsers/maxpool_parser.py
onnx_to_gurobi/parsers/parser_factory.py
onnx_to_gurobi/parsers/relu_parser.py
onnx_to_gurobi/parsers/reshape_parser.py
onnx_to_gurobi/parsers/shape_parser.py
onnx_to_gurobi/parsers/sub_parser.py
onnx_to_gurobi/parsers/unsqueeze_parser.py
onnxgurobi-0.1.3.dist-info/licenses/LICENSE.txt
onnxgurobi-0.1.3.dist-info/METADATA
onnxgurobi-0.1.3.dist-info/WHEEL
onnxgurobi-0.1.3.dist-info/top_level.txt
onnxgurobi-0.1.3.dist-info/RECORD
