Metadata-Version: 2.4
Name: onnxgurobi
Version: 0.1.3
Summary: The onnx_to_gurobi is a Python library that creates Gurobi models for neural networks in ONNX format.
Author-email: Muhammad Atallah <muhammad.sabri@outlook.com>
License-Expression: MIT
Project-URL: Homepage, https://yourhomepage.example.com/
Project-URL: Repository, https://github.com/yourusername/onnx_gurobi
Classifier: Programming Language :: Python :: 3
Classifier: Programming Language :: Python :: 3.11
Classifier: Programming Language :: Python :: 3.12
Classifier: Operating System :: OS Independent
Requires-Python: >=3.11
License-File: LICENSE.txt
Requires-Dist: numpy>=1.26.4
Requires-Dist: onnx>=1.16.2
Requires-Dist: onnxruntime>=1.20.1
Requires-Dist: torch>=2.5.1
Requires-Dist: pytest>=8.3.5
Requires-Dist: tensorflow>=2.19.0
Requires-Dist: matplotlib>=3.10.1
Dynamic: license-file
